styler_identity/__init__.py
styler_identity/identity.py
styler_identity-0.5.3.dist-info/LICENSE
styler_identity-0.5.3.dist-info/METADATA
styler_identity-0.5.3.dist-info/WHEEL
styler_identity-0.5.3.dist-info/top_level.txt
styler_identity-0.5.3.dist-info/RECORD
